{
  "publicPath": "/dist/",
  "all": [
    "9.cd8e4090a37bda00b734.js",
    "ClearSans.b9bdac5.ttf",
    "Ubuntu.8f38bca.ttf",
    "UbuntuBold.0356dd2.ttf",
    "0.d763b4cf0bc81c5ac272.js",
    "1.3a28b9ebd539d80c077b.js",
    "2.419218c0bd601040c689.js",
    "3.28ce4034770d4411371e.js",
    "4.81623e4d64a87af3e7d8.js",
    "5.c252b855c14d2e903511.js",
    "6.7198afd480a31eb7989e.js",
    "7.432d86625269cbeceba7.js",
    "8.6b30c41aa9f8ec64dfa2.js",
    "ClearSans-Bold.79e0c29.ttf",
    "10.7f23e46e6d5386654bfe.js",
    "11.26cce2d92d5585ef7f55.js",
    "12.9f0638cb49002c304260.js",
    "13.50aa463aab81fd41ab01.js",
    "14.9bc06b2296934e542fc7.js",
    "15.5dbb7adf16bbc67b93bc.js",
    "16.36ac9f7bf3bcf560da51.js",
    "vendor.8a85e92a565cee334077.bundle.js",
    "app.009687bf47453a7eb8f1.bundle.js",
    "manifest.06392060c4e0b1fff998.bundle.js",
    "common.009687bf47453a7eb8f1.css",
    "common.009687bf47453a7eb8f1.css.map"
  ],
  "initial": [
    "manifest.06392060c4e0b1fff998.bundle.js",
    "vendor.8a85e92a565cee334077.bundle.js",
    "app.009687bf47453a7eb8f1.bundle.js",
    "common.009687bf47453a7eb8f1.css"
  ],
  "async": [
    "9.cd8e4090a37bda00b734.js",
    "0.d763b4cf0bc81c5ac272.js",
    "1.3a28b9ebd539d80c077b.js",
    "2.419218c0bd601040c689.js",
    "3.28ce4034770d4411371e.js",
    "4.81623e4d64a87af3e7d8.js",
    "5.c252b855c14d2e903511.js",
    "6.7198afd480a31eb7989e.js",
    "7.432d86625269cbeceba7.js",
    "8.6b30c41aa9f8ec64dfa2.js",
    "10.7f23e46e6d5386654bfe.js",
    "11.26cce2d92d5585ef7f55.js",
    "12.9f0638cb49002c304260.js",
    "13.50aa463aab81fd41ab01.js",
    "14.9bc06b2296934e542fc7.js",
    "15.5dbb7adf16bbc67b93bc.js",
    "16.36ac9f7bf3bcf560da51.js"
  ],
  "modules": {
    "38193544": [
      21
    ],
    "41209771": [
      7
    ],
    "43716033": [
      21
    ],
    "51889678": [
      21
    ],
    "53154858": [
      21
    ],
    "55635212": [
      21
    ],
    "57708308": [
      12
    ],
    "72388403": [
      22,
      24,
      25
    ],
    "74297200": [
      21
    ],
    "74935046": [
      4
    ],
    "75164192": [
      21
    ],
    "77146482": [
      4
    ],
    "079460d9": [
      21
    ],
    "2170b69f": [
      21
    ],
    "0927e43c": [
      21
    ],
    "0586b68a": [
      21
    ],
    "c5c1f3bc": [
      21
    ],
    "663fd228": [
      21
    ],
    "7542f9a9": [
      21
    ],
    "1eca91f2": [
      21
    ],
    "9a173c52": [
      21
    ],
    "94a579ba": [
      21
    ],
    "703181fc": [
      21
    ],
    "443e425b": [
      22,
      24,
      25
    ],
    "46f7b78f": [
      21
    ],
    "3f58a96a": [
      21
    ],
    "d0619dfe": [
      21
    ],
    "518563e4": [
      21
    ],
    "4e088986": [
      21
    ],
    "78a9e9c4": [
      21
    ],
    "1687efe4": [
      21
    ],
    "2dc15bea": [
      21
    ],
    "fa0d2c72": [
      21
    ],
    "a7a28166": [
      21
    ],
    "715ec292": [
      21
    ],
    "228006b0": [
      21
    ],
    "3b9e9939": [
      21
    ],
    "3b3d54cc": [
      21
    ],
    "7b7f331a": [
      21
    ],
    "13eeb5ab": [
      21
    ],
    "55356c92": [
      21
    ],
    "0190fea6": [
      21
    ],
    "0c625581": [
      21
    ],
    "f502d1c8": [
      21
    ],
    "561ad71f": [
      21
    ],
    "7be726a1": [
      21
    ],
    "28aa8330": [
      21
    ],
    "4474830c": [
      21
    ],
    "3266fe3e": [
      21
    ],
    "7da994a6": [
      21
    ],
    "55b96a10": [
      21
    ],
    "28baf2e4": [
      21
    ],
    "0ee535f8": [
      21
    ],
    "ccdb575e": [
      21
    ],
    "874799f4": [
      21
    ],
    "c387286e": [
      21
    ],
    "bc4c6210": [
      21
    ],
    "cf1934c2": [
      21
    ],
    "228ff6cc": [
      21
    ],
    "4cc6c251": [
      22,
      24,
      25
    ],
    "479df3ea": [
      21
    ],
    "44f6417e": [
      21
    ],
    "4c19844b": [
      21
    ],
    "bba64b68": [
      21
    ],
    "7b308ee7": [
      21
    ],
    "d4bdf05a": [
      21
    ],
    "af2fd288": [
      21
    ],
    "c3980988": [
      21
    ],
    "27f75df5": [
      21
    ],
    "159652c4": [
      21
    ],
    "75e0b9c6": [
      21
    ],
    "3b2dd665": [
      21
    ],
    "44be7790": [
      21
    ],
    "f05bccfe": [
      21
    ],
    "ae0cf750": [
      21
    ],
    "552c5526": [
      21
    ],
    "9ec0c2d2": [
      21
    ],
    "6b77e523": [
      21
    ],
    "36ebcb4f": [
      21
    ],
    "a1ab7a4a": [
      21
    ],
    "2f3bdbb7": [
      21
    ],
    "762f5df9": [
      21
    ],
    "a7e1cfec": [
      21
    ],
    "b3bed3d2": [
      21
    ],
    "d77b01a0": [
      21
    ],
    "5020ec25": [
      21
    ],
    "dfbb82f0": [
      21
    ],
    "cde53dd0": [
      21
    ],
    "9ca857a0": [
      21
    ],
    "63c4341c": [
      21
    ],
    "43fb82a9": [
      21
    ],
    "242b945c": [
      21
    ],
    "276e6aaf": [
      21
    ],
    "5527c970": [
      21
    ],
    "84ce56ac": [
      21
    ],
    "648276b0": [
      21
    ],
    "74a84f5b": [
      21
    ],
    "1b074624": [
      22,
      24,
      25
    ],
    "615cdd07": [
      21
    ],
    "e65bb74e": [
      21
    ],
    "20ab7257": [
      21
    ],
    "ec8c5a3c": [
      21
    ],
    "0b391412": [
      21
    ],
    "6aef3349": [
      21
    ],
    "0a11c6a7": [
      21
    ],
    "fc2211b2": [
      21
    ],
    "33764e4f": [
      21
    ],
    "538a30c6": [
      21
    ],
    "7c4e8f77": [
      21
    ],
    "9033488e": [
      21
    ],
    "4a3ed8ee": [
      21
    ],
    "26de6c94": [
      21
    ],
    "72d66688": [
      21
    ],
    "26c86a36": [
      21
    ],
    "6cd39532": [
      21
    ],
    "51e19430": [
      21
    ],
    "8183084e": [
      21
    ],
    "57196ee8": [
      21
    ],
    "72f14a3a": [
      21
    ],
    "17dfaecd": [
      21
    ],
    "02dc8928": [
      21
    ],
    "e549f4a8": [
      21
    ],
    "fa670b4a": [
      21
    ],
    "47b63b02": [
      21
    ],
    "22f27351": [
      21
    ],
    "6e04aa17": [
      21
    ],
    "ea9ce026": [
      21
    ],
    "5a47e9ec": [
      22,
      24,
      25
    ],
    "e42b86a6": [
      21
    ],
    "03b98e85": [
      21
    ],
    "59a68a12": [
      21
    ],
    "2b7f9fb4": [
      21
    ],
    "36b7ff18": [
      21
    ],
    "f38d7d70": [
      21
    ],
    "fa07d194": [
      21
    ],
    "7adccaac": [
      21
    ],
    "6dc6f08d": [
      21
    ],
    "04c32125": [
      21
    ],
    "0732b9fc": [
      21
    ],
    "f5570852": [
      21
    ],
    "57604f20": [
      21
    ],
    "66cbd891": [
      21
    ],
    "2251ea72": [
      21
    ],
    "7c819abb": [
      21
    ],
    "2e1d4b64": [
      21
    ],
    "3cfa5478": [
      21
    ],
    "e1cfa60c": [
      21
    ],
    "f2536cd6": [
      21
    ],
    "4f63445c": [
      21
    ],
    "18e15154": [
      21
    ],
    "0f18994e": [
      21
    ],
    "7b84cb19": [
      21
    ],
    "2c3deefa": [
      21
    ],
    "41a69952": [
      21
    ],
    "68cb902c": [
      21
    ],
    "7854f495": [
      21
    ],
    "04d7683a": [
      21
    ],
    "5b0c7492": [
      21
    ],
    "0b761baf": [
      21
    ],
    "4dc4ac2c": [
      21
    ],
    "0bd12dd6": [
      21
    ],
    "83d3b72a": [
      21
    ],
    "5bf082fa": [
      22,
      24,
      25
    ],
    "30bcfb23": [
      21
    ],
    "af96baf2": [
      21
    ],
    "2bd65b28": [
      21
    ],
    "134eb470": [
      21
    ],
    "9d04c0c0": [
      21
    ],
    "47dafeb6": [
      21
    ],
    "57bbd403": [
      21
    ],
    "d630db2e": [
      21
    ],
    "4cef8951": [
      21
    ],
    "5621edf7": [
      21
    ],
    "9b22c02e": [
      21
    ],
    "532f6c02": [
      21
    ],
    "88f7eaf4": [
      21
    ],
    "672b3fcb": [
      21
    ],
    "81988ed6": [
      21
    ],
    "651dbb70": [
      21
    ],
    "c311a36e": [
      21
    ],
    "0d304c9a": [
      21
    ],
    "58922d94": [
      22,
      24,
      25
    ],
    "0251575f": [
      22,
      24,
      25
    ],
    "5da22d8d": [
      22,
      24,
      25
    ],
    "78eea5e8": [
      22,
      24,
      25
    ],
    "5bea4c90": [
      22,
      24,
      25
    ],
    "5c9fdfa6": [
      22,
      24,
      25
    ],
    "322ff449": [
      22,
      24,
      25
    ],
    "31eeab96": [
      22,
      24,
      25
    ],
    "7e3e7b24": [
      22,
      24,
      25
    ],
    "7487548d": [
      21
    ],
    "fc269d68": [
      21
    ],
    "9d0ab238": [
      22,
      24,
      25
    ],
    "5f5365f0": [
      22,
      24,
      25
    ],
    "cdf35ac4": [
      22,
      24,
      25
    ],
    "0856c132": [
      21
    ],
    "dcd39dc4": [
      21
    ],
    "3851b475": [
      21
    ],
    "78be35e3": [
      21
    ],
    "cb2106a2": [
      21
    ],
    "61e14072": [
      21
    ],
    "bb9f278c": [
      21
    ],
    "24e92276": [
      21
    ],
    "39196dc4": [
      21
    ],
    "b9e1a968": [
      21
    ],
    "fba51888": [
      21
    ],
    "2b84f7b2": [
      21
    ],
    "b12af03c": [
      21
    ],
    "56bf1c64": [
      21
    ],
    "1e4ded5f": [
      21
    ],
    "13a8b183": [
      21
    ],
    "22daa594": [
      21
    ],
    "2b27c64c": [
      21
    ],
    "1634b8e8": [
      21
    ],
    "528384a0": [
      21
    ],
    "c45adee8": [
      21
    ],
    "3c7c805f": [
      21
    ],
    "048f19d4": [
      21
    ],
    "8e6b15a6": [
      21
    ],
    "565c141c": [
      21
    ],
    "116e1633": [
      21
    ],
    "f2360062": [
      21
    ],
    "2e25fa50": [
      21
    ],
    "6d472f16": [
      21
    ],
    "52a4e504": [
      21
    ],
    "77be7250": [
      21
    ],
    "339417f5": [
      21
    ],
    "3e0b5b2f": [
      21
    ],
    "707ca215": [
      21
    ],
    "7629770c": [
      21
    ],
    "a77335a0": [
      21
    ],
    "10f9963c": [
      21
    ],
    "3e29da2c": [
      21
    ],
    "acd35fa6": [
      21
    ],
    "2ec2627a": [
      21
    ],
    "a9db532e": [
      21
    ],
    "31dac405": [
      21
    ],
    "694bf320": [
      21
    ],
    "907c393c": [
      21
    ],
    "83df10be": [
      21
    ],
    "0d4031c4": [
      21
    ],
    "59f69977": [
      21
    ],
    "050b1038": [
      21
    ],
    "5796a6a0": [
      21
    ],
    "05a03627": [
      21
    ],
    "8076e0f8": [
      21
    ],
    "14323b78": [
      21
    ],
    "5acf17e1": [
      21
    ],
    "7665fb68": [
      21
    ],
    "0bc81026": [
      21
    ],
    "aebdc30c": [
      21
    ],
    "10a8d4a8": [
      21
    ],
    "55338e6c": [
      21
    ],
    "9f0e0c26": [
      21
    ],
    "c68fbb3c": [
      21
    ],
    "0286732a": [
      21
    ],
    "65eb98cf": [
      21
    ],
    "026f1b35": [
      21
    ],
    "31bafcf4": [
      21
    ],
    "642dc8d9": [
      21
    ],
    "b2f9ef94": [
      21
    ],
    "2ee545b1": [
      21
    ],
    "056028f1": [
      21
    ],
    "7eba9686": [
      21
    ],
    "11df57ae": [
      21
    ],
    "1bd25f1a": [
      21
    ],
    "fb20e7d2": [
      21
    ],
    "10a6e03e": [
      21
    ],
    "24a98e6a": [
      21
    ],
    "33a4808c": [
      21
    ],
    "d0bfb888": [
      21
    ],
    "5ad338dc": [
      21
    ],
    "7a302ded": [
      21
    ],
    "1317e647": [
      21
    ],
    "bc4e1a36": [
      21
    ],
    "5f665b1d": [
      21
    ],
    "39ffc460": [
      21
    ],
    "36c09a44": [
      21
    ],
    "4ff88eae": [
      21
    ],
    "69ce8aee": [
      21
    ],
    "4fe002a4": [
      21
    ],
    "1f11946f": [
      21
    ],
    "0af09f52": [
      21
    ],
    "3d4d0280": [
      21
    ],
    "2301ba56": [
      21
    ],
    "5adb29d8": [
      21
    ],
    "56b3f3b4": [
      21
    ],
    "fe831a40": [
      21
    ],
    "76c2c49e": [
      21
    ],
    "2843d80c": [
      21
    ],
    "5be4924b": [
      21
    ],
    "3bbfc472": [
      21
    ],
    "721c356b": [
      21
    ],
    "786d4de1": [
      21
    ],
    "d324c4b8": [
      21
    ],
    "3c8d2634": [
      21
    ],
    "359c98c4": [
      21
    ],
    "a7942f9e": [
      21
    ],
    "60f0f63f": [
      21
    ],
    "60d3de7f": [
      21
    ],
    "4d72a49e": [
      21
    ],
    "94c71422": [
      21
    ],
    "94073f88": [
      21
    ],
    "458852f6": [
      21
    ],
    "59e69896": [
      21
    ],
    "4182ec1d": [
      21
    ],
    "0621385c": [
      21
    ],
    "12b09672": [
      21
    ],
    "efaa92ce": [
      21
    ],
    "67df5acc": [
      21
    ],
    "92a66c56": [
      21
    ],
    "41f883ec": [
      21
    ],
    "357bf70c": [
      22,
      24,
      25
    ],
    "950387cc": [
      21
    ],
    "1667c834": [
      21
    ],
    "02f48a8b": [
      22,
      24,
      25
    ],
    "78875dfc": [
      21
    ],
    "25b49c42": [
      21
    ],
    "5f01a930": [
      22,
      24,
      25
    ],
    "7adecdd2": [
      22,
      24,
      25
    ],
    "134cf98a": [
      21
    ],
    "8acc67e2": [
      21
    ],
    "529ce0f1": [
      21
    ],
    "f97dcce2": [
      21
    ],
    "30ad51d5": [
      21
    ],
    "35ca0a36": [
      21
    ],
    "e9029710": [
      21
    ],
    "5d45a3f6": [
      21
    ],
    "685696bf": [
      21
    ],
    "67c945b8": [
      21
    ],
    "4eafb62b": [
      21
    ],
    "6e91aada": [
      21
    ],
    "0c30bc26": [
      21
    ],
    "040ef551": [
      21
    ],
    "a9778972": [
      21
    ],
    "61a33e56": [
      21
    ],
    "160157d7": [
      21
    ],
    "6928fe2a": [
      21
    ],
    "2ff2244c": [
      21
    ],
    "5e2eb00f": [
      21
    ],
    "1f0342f0": [
      21
    ],
    "4a268d62": [
      21
    ],
    "248ba12a": [
      21
    ],
    "7886d466": [
      21
    ],
    "79d6bd39": [
      21
    ],
    "cd26f88e": [
      21
    ],
    "b111e5f4": [
      21
    ],
    "c1781a3e": [
      21
    ],
    "5597a372": [
      21
    ],
    "1b7ea8f8": [
      21
    ],
    "2cd1e4e7": [
      21
    ],
    "b2001416": [
      21
    ],
    "9dc518d6": [
      21
    ],
    "79fd4904": [
      21
    ],
    "e3249f92": [
      21
    ],
    "3fdb240a": [
      21
    ],
    "c77273f2": [
      21
    ],
    "7b0561b4": [
      21
    ],
    "13f99b90": [
      21
    ],
    "63f4c003": [
      21
    ],
    "8fdb697c": [
      21
    ],
    "5db252d6": [
      21
    ],
    "af55c170": [
      22,
      24,
      25
    ],
    "d7f95c4a": [
      22,
      24,
      25
    ],
    "46d647e8": [
      22,
      24,
      25
    ],
    "6b79a544": [
      22,
      24,
      25
    ],
    "1c205878": [
      22,
      24,
      25
    ],
    "b23a4cf0": [
      22,
      24,
      25
    ],
    "55efd652": [
      22,
      24,
      25
    ],
    "80e1e142": [
      22,
      24,
      25
    ],
    "890da004": [
      22,
      24,
      25
    ],
    "5cbf0572": [
      22,
      24,
      25
    ],
    "14aeaa76": [
      22,
      24,
      25
    ],
    "468ff629": [
      22,
      24,
      25
    ],
    "2f37fb2d": [
      22,
      24,
      25
    ],
    "393b0e8d": [
      22,
      24,
      25
    ],
    "313975f7": [
      22,
      24,
      25
    ],
    "83b8ac3c": [
      22,
      24,
      25
    ],
    "d942899a": [
      22,
      24,
      25
    ],
    "5120d5e3": [
      22,
      24,
      25
    ],
    "80aaae6c": [
      22,
      24,
      25
    ],
    "1cec484b": [
      22,
      24,
      25
    ],
    "7bf5eac7": [
      22,
      24,
      25
    ],
    "03580323": [
      22,
      24,
      25
    ],
    "53bf5872": [
      22,
      24,
      25
    ],
    "22b902b0": [
      22,
      24,
      25
    ],
    "1b89d78a": [
      22,
      24,
      25
    ],
    "f46fb652": [
      22,
      24,
      25
    ],
    "feedcf10": [
      22,
      24,
      25
    ],
    "7101b1c2": [
      22,
      24,
      25
    ],
    "02110501": [
      22,
      24,
      25
    ],
    "4d38efc4": [
      22,
      24,
      25
    ],
    "782ed1b6": [
      22,
      24,
      25
    ],
    "00b1d1f6": [
      22,
      24,
      25
    ],
    "7bcc345e": [
      21
    ],
    "ed82e21a": [
      22,
      24,
      25
    ],
    "5dc83258": [
      22,
      24,
      25
    ],
    "573666db": [
      22,
      24,
      25
    ],
    "2d0c13a6": [
      21
    ],
    "b324658c": [
      21
    ],
    "0829c87a": [
      21
    ],
    "5bea34b0": [
      22,
      24,
      25
    ],
    "d9d34e1a": [
      22,
      24,
      25
    ],
    "641fb3ec": [
      22,
      24,
      25
    ],
    "08d39134": [
      22,
      24,
      25
    ],
    "4c4627a6": [
      22,
      24,
      25
    ],
    "6ccd9b7b": [
      22,
      24,
      25
    ],
    "3dd6f674": [
      22,
      24,
      25
    ],
    "05e2edba": [
      22,
      24,
      25
    ],
    "52276e9a": [
      22,
      24,
      25
    ],
    "010615bd": [
      22,
      24,
      25
    ],
    "5be11e94": [
      22,
      24,
      25
    ],
    "00498860": [
      22,
      24,
      25
    ],
    "5d5a394e": [
      22,
      24,
      25
    ],
    "7db88e12": [
      22,
      24,
      25
    ],
    "4ec1e90b": [
      22,
      24,
      25
    ],
    "4b13b791": [
      22,
      24,
      25
    ],
    "1c1d128a": [
      22,
      24,
      25
    ],
    "f096927c": [
      22,
      24,
      25
    ],
    "58be11bb": [
      22,
      24,
      25
    ],
    "fbb438ee": [
      22,
      24,
      25
    ],
    "532f3e82": [
      22,
      24,
      25
    ],
    "fe093916": [
      22,
      24,
      25
    ],
    "5204be6e": [
      22,
      24,
      25
    ],
    "4f1d3185": [
      22,
      24,
      25
    ],
    "20268c7e": [
      22,
      24,
      25
    ],
    "78736f68": [
      22,
      24,
      25
    ],
    "3d3430c3": [
      22,
      24,
      25
    ],
    "3079cf79": [
      21
    ],
    "93c786e0": [
      21
    ],
    "4971457a": [
      21
    ],
    "5260a78d": [
      21
    ],
    "4fb02fac": [
      21
    ],
    "f25956d0": [
      21
    ],
    "f4515f14": [
      21
    ],
    "5e8a51ba": [
      21
    ],
    "46ffef69": [
      21
    ],
    "6bc55f80": [
      21
    ],
    "3e917750": [
      21
    ],
    "31689f78": [
      21
    ],
    "fc2fb4d4": [
      21
    ],
    "60ef46fd": [
      21
    ],
    "270d3e59": [
      21
    ],
    "0ef84bd6": [
      21
    ],
    "142f9618": [
      21
    ],
    "3c12452f": [
      22,
      24,
      25
    ],
    "f39957c2": [
      21
    ],
    "0f72c40b": [
      21
    ],
    "7ac02981": [
      21
    ],
    "03a8808b": [
      21
    ],
    "1a5c19a9": [
      22,
      24,
      25
    ],
    "1c78cf3a": [
      21
    ],
    "33072c4e": [
      21
    ],
    "6092db02": [
      21
    ],
    "b4948cfe": [
      21
    ],
    "0bf9ec2a": [
      21
    ],
    "f3145120": [
      20
    ],
    "5e12985a": [
      19
    ],
    "7d868de4": [
      14
    ],
    "3d8996d9": [
      0
    ],
    "b557d2b0": [
      11
    ],
    "ac29da82": [
      9
    ],
    "02ad2408": [
      16
    ],
    "109b86de": [
      8
    ],
    "d986c4f0": [
      15
    ],
    "8f6c06c8": [
      17
    ],
    "0f5ebf1c": [
      10
    ],
    "c84d6110": [
      7
    ],
    "7acd8d1b": [
      6
    ],
    "803930b4": [
      18
    ],
    "4cf7402e": [
      21
    ],
    "7d719ff5": [
      20
    ],
    "8faf4a16": [
      19
    ],
    "6e102d07": [
      4
    ],
    "0659cd7a": [
      4
    ],
    "ccb5fd98": [
      4
    ],
    "f5fc263a": [
      4
    ],
    "41212e80": [
      4
    ],
    "233d34d8": [
      4
    ],
    "85d04230": [
      4
    ],
    "2e5e8cba": [
      4
    ],
    "9828ba58": [
      4
    ],
    "cb5bd9fe": [
      4
    ],
    "898faadc": [
      4
    ],
    "3d36b45b": [
      4
    ],
    "7be71f40": [
      4
    ],
    "98f8effe": [
      12
    ],
    "6921a9dc": [
      12
    ],
    "8fafbe1e": [
      12
    ],
    "6d0bbfae": [
      14
    ],
    "07e4f69f": [
      14
    ],
    "1cc5605e": [
      0
    ],
    "2a772705": [
      0
    ],
    "a4dd047a": [
      11
    ],
    "9c8a6668": [
      11
    ],
    "328bffc6": [
      11
    ],
    "3e48f178": [
      9
    ],
    "d04e60b2": [
      9
    ],
    "7f376386": [
      9
    ],
    "76d9baa3": [
      16
    ],
    "bc35058e": [
      8
    ],
    "60ce3fc8": [
      8
    ],
    "936ceef0": [
      8
    ],
    "e352c3ba": [
      15
    ],
    "5f6818b7": [
      17
    ],
    "13b1fc4d": [
      10
    ],
    "71e3b71c": [
      10
    ],
    "4e7b0a72": [
      10
    ],
    "5a24fcd3": [
      7
    ],
    "4fc222ef": [
      7
    ],
    "01f393a5": [
      7
    ],
    "34bbb2e0": [
      6
    ],
    "441d1f3c": [
      6
    ],
    "e9a4166e": [
      6
    ],
    "9fde5572": [
      6
    ],
    "518a0c8f": [
      6
    ],
    "69e534aa": [
      18
    ],
    "7f2e6c3a": [
      20
    ],
    "536a7c8e": [
      19
    ],
    "2a025d54": [
      19
    ],
    "83b86998": [
      19
    ],
    "0168c061": [
      4
    ],
    "553f0fe6": [
      4
    ],
    "24d84e75": [
      4
    ],
    "e6c85bda": [
      4
    ],
    "fd114fd0": [
      4
    ],
    "510b02de": [
      4
    ],
    "12872f6f": [
      4
    ],
    "160ec82f": [
      4
    ],
    "4220e0f4": [
      4
    ],
    "3affd4b6": [
      4
    ],
    "d2fc3ef0": [
      4
    ],
    "322ddb3f": [
      4
    ],
    "7311fecc": [
      4
    ],
    "50e5e36c": [
      4
    ],
    "02750ffb": [
      4
    ],
    "9c8820cc": [
      4
    ],
    "226187c2": [
      4
    ],
    "1affcdbd": [
      4
    ],
    "6a2f7492": [
      4
    ],
    "2b8d24a6": [
      4
    ],
    "4447d53a": [
      4
    ],
    "7b60562a": [
      4
    ],
    "4df54daf": [
      4
    ],
    "21bdc3c6": [
      4
    ],
    "52150a07": [
      4
    ],
    "61b2e7de": [
      4
    ],
    "2ce21b5e": [
      4
    ],
    "15a10b16": [
      4
    ],
    "0145a512": [
      4
    ],
    "7528d30e": [
      4
    ],
    "4b8af903": [
      4
    ],
    "4057c344": [
      4
    ],
    "371b2208": [
      4
    ],
    "4ba3b166": [
      4
    ],
    "5194bfe4": [
      4
    ],
    "0fac0b02": [
      4
    ],
    "20d6a041": [
      4
    ],
    "668fc392": [
      4
    ],
    "8b56d1ca": [
      4
    ],
    "4e9dbc76": [
      4
    ],
    "2dbe482c": [
      4
    ],
    "4eb6a800": [
      4
    ],
    "7b44f7bb": [
      4
    ],
    "0f8e1d16": [
      4
    ],
    "eed43f84": [
      4
    ],
    "0b4d1c5b": [
      4
    ],
    "33b727e6": [
      4
    ],
    "34d2ac2a": [
      4
    ],
    "1f488651": [
      4
    ],
    "ecc5cdec": [
      4
    ],
    "1b30bd84": [
      12
    ],
    "61e20e09": [
      12
    ],
    "f0bfaa52": [
      12
    ],
    "ef6e4a38": [
      12
    ],
    "de46f02e": [
      12
    ],
    "750bb5ea": [
      12
    ],
    "d2061754": [
      12
    ],
    "6bb6e8fc": [
      12
    ],
    "ffc0ddc6": [
      12
    ],
    "7bca247a": [
      12
    ],
    "66e305bb": [
      12
    ],
    "520fa6ae": [
      14
    ],
    "3cef326e": [
      14
    ],
    "2663779a": [
      14
    ],
    "43e921a0": [
      14
    ],
    "4c7ccea5": [
      14
    ],
    "7f903bb5": [
      14
    ],
    "b3524df2": [
      14
    ],
    "c3f870d0": [
      0
    ],
    "3695cfc6": [
      0
    ],
    "18f29b00": [
      0
    ],
    "235f9979": [
      0
    ],
    "309b3bfe": [
      0
    ],
    "7893b870": [
      0
    ],
    "5b2b3581": [
      0
    ],
    "580563a3": [
      11
    ],
    "3103b884": [
      11
    ],
    "2a9cfb07": [
      11
    ],
    "a67728d2": [
      11
    ],
    "41be2948": [
      11
    ],
    "e1a4fdd0": [
      11
    ],
    "3b00cd50": [
      11
    ],
    "d5fdd352": [
      11
    ],
    "c33277c8": [
      11
    ],
    "b140ed00": [
      11
    ],
    "04aaa834": [
      11
    ],
    "1e2aaa6b": [
      9
    ],
    "2b664cf0": [
      9
    ],
    "7c7773cc": [
      9
    ],
    "2b532776": [
      9
    ],
    "0b1cda20": [
      9
    ],
    "65b83bb2": [
      9
    ],
    "0b0acceb": [
      9
    ],
    "3a3ca54e": [
      9
    ],
    "368fd5f4": [
      9
    ],
    "735758fc": [
      9
    ],
    "e6b84418": [
      9
    ],
    "2c8eb6b6": [
      16
    ],
    "3d66cd40": [
      16
    ],
    "5f9a3f0a": [
      16
    ],
    "136f5f40": [
      8
    ],
    "6d45679b": [
      8
    ],
    "d41a3fd2": [
      8
    ],
    "22eac49c": [
      8
    ],
    "6718cbb7": [
      8
    ],
    "3bb641fd": [
      8
    ],
    "59ad21ad": [
      8
    ],
    "0804cf1c": [
      8
    ],
    "522e984d": [
      8
    ],
    "2ffa8897": [
      8
    ],
    "84d305be": [
      8
    ],
    "6e53258a": [
      8
    ],
    "06fce1a0": [
      15
    ],
    "bf97178a": [
      15
    ],
    "330d3ea2": [
      15
    ],
    "5ced2746": [
      17
    ],
    "11b4553e": [
      17
    ],
    "46737b1e": [
      17
    ],
    "65bfac62": [
      10
    ],
    "f2f3cb86": [
      10
    ],
    "4c223bd2": [
      10
    ],
    "bfbd8858": [
      10
    ],
    "fde7824e": [
      10
    ],
    "1f37aa9b": [
      10
    ],
    "0066ae52": [
      10
    ],
    "7c3502d4": [
      10
    ],
    "22ca3d6f": [
      10
    ],
    "024e9c53": [
      10
    ],
    "6b8299fe": [
      10
    ],
    "c314f04e": [
      7
    ],
    "51f56398": [
      7
    ],
    "2e96f654": [
      7
    ],
    "50af1130": [
      7
    ],
    "61b93603": [
      7
    ],
    "352b2cff": [
      7
    ],
    "6b1be18a": [
      7
    ],
    "789ca28c": [
      7
    ],
    "e15ecd48": [
      7
    ],
    "af8b7560": [
      7
    ],
    "0b29ad5a": [
      6
    ],
    "77acd3d0": [
      6
    ],
    "72029a44": [
      6
    ],
    "22f1f2a1": [
      6
    ],
    "6db68756": [
      6
    ],
    "53357af0": [
      6
    ],
    "4286a6a8": [
      6
    ],
    "f218e3f8": [
      6
    ],
    "277ef497": [
      6
    ],
    "40f3ed48": [
      6
    ],
    "3f721fb2": [
      6
    ],
    "a85322fc": [
      6
    ],
    "4ce07702": [
      6
    ],
    "04e78bc7": [
      6
    ],
    "5d6a40ba": [
      6
    ],
    "1ae7ea34": [
      6
    ],
    "67ab8b61": [
      6
    ],
    "4368c6bc": [
      6
    ],
    "6dd7f4c0": [
      6
    ],
    "67a0c82c": [
      6
    ],
    "426b0111": [
      18
    ],
    "8a5da5d4": [
      18
    ],
    "4ae009bc": [
      18
    ]
  }
}